WDPhotTools/__init__.py
WDPhotTools/atmosphere_model_reader.py
WDPhotTools/cooling_model_reader.py
WDPhotTools/diff2_functions_least_square.py
WDPhotTools/diff2_functions_minimize.py
WDPhotTools/extinction.py
WDPhotTools/fitter.py
WDPhotTools/likelihood_functions.py
WDPhotTools/plotter.py
WDPhotTools/reddening.py
WDPhotTools/theoretical_lf.py
WDPhotTools/util.py
WDPhotTools/extinction/B.csv
WDPhotTools/extinction/FUV.csv
WDPhotTools/extinction/G2.csv
WDPhotTools/extinction/G2_BP.csv
WDPhotTools/extinction/G2_RP.csv
WDPhotTools/extinction/G3.csv
WDPhotTools/extinction/G3_BP.csv
WDPhotTools/extinction/G3_RP.csv
WDPhotTools/extinction/H.csv
WDPhotTools/extinction/H_mko.csv
WDPhotTools/extinction/I.csv
WDPhotTools/extinction/J.csv
WDPhotTools/extinction/J_mko.csv
WDPhotTools/extinction/K_mko.csv
WDPhotTools/extinction/Ks.csv
WDPhotTools/extinction/NUV.csv
WDPhotTools/extinction/R.csv
WDPhotTools/extinction/S36.csv
WDPhotTools/extinction/S45.csv
WDPhotTools/extinction/S58.csv
WDPhotTools/extinction/S80.csv
WDPhotTools/extinction/U.csv
WDPhotTools/extinction/V.csv
WDPhotTools/extinction/W1.csv
WDPhotTools/extinction/W2.csv
WDPhotTools/extinction/W3.csv
WDPhotTools/extinction/W4.csv
WDPhotTools/extinction/Y_mko.csv
WDPhotTools/extinction/g_ps1.csv
WDPhotTools/extinction/g_sdss.csv
WDPhotTools/extinction/generate_extinction_table.py
WDPhotTools/extinction/i_ps1.csv
WDPhotTools/extinction/i_sdss.csv
WDPhotTools/extinction/r_ps1.csv
WDPhotTools/extinction/r_sdss.csv
WDPhotTools/extinction/schlafly12.csv
WDPhotTools/extinction/u_sdss.csv
WDPhotTools/extinction/y_ps1.csv
WDPhotTools/extinction/z_ps1.csv
WDPhotTools/extinction/z_sdss.csv
WDPhotTools/ms_lifetime/MISTv1p2Fe000.csv
WDPhotTools/ms_lifetime/MISTv1p2Fe025.csv
WDPhotTools/ms_lifetime/MISTv1p2Fe050.csv
WDPhotTools/ms_lifetime/MISTv1p2Fem025.csv
WDPhotTools/ms_lifetime/MISTv1p2Fem050.csv
WDPhotTools/ms_lifetime/MISTv1p2Fem075.csv
WDPhotTools/ms_lifetime/MISTv1p2Fem100.csv
WDPhotTools/ms_lifetime/MISTv1p2Fem125.csv
wdphottools-0.0.13.dist-info/licenses/LICENSE
wdphottools-0.0.13.dist-info/METADATA
wdphottools-0.0.13.dist-info/WHEEL
wdphottools-0.0.13.dist-info/top_level.txt
wdphottools-0.0.13.dist-info/RECORD
