Metadata-Version: 2.4
Name: wdphottools
Version: 0.0.13
Summary: A White Dwarf Photometric Toolkit in Python
Home-page: https://wdphottools.readthedocs.io/en/latest/?badge=latest
Download-URL: https://github.com/cylammarco/WDPhotTools
Author: Marco C Lam
Author-email: mlam@roe.ac.uk
Maintainer: Marco C Lam
Maintainer-email: mlam@roe.ac.uk
License: BSD-3-Clause
Classifier: License :: OSI Approved :: BSD License
Classifier: Programming Language :: Python :: 3
Classifier: Programming Language :: Python :: 3.10
Classifier: Programming Language :: Python :: 3.11
Classifier: Programming Language :: Python :: 3.12
Classifier: Programming Language :: Python :: 3.13
Classifier: Programming Language :: Python :: 3.14
Classifier: Operating System :: OS Independent
Requires-Python: >=3.10
License-File: LICENSE
Requires-Dist: numpy>=1.23
Requires-Dist: scipy>=1.7.3
Requires-Dist: matplotlib>=3.5
Requires-Dist: emcee>=3.0
Requires-Dist: corner>2.2
Requires-Dist: astropy>=4.3
Dynamic: download-url
Dynamic: license-file
